upbankapi/__init__.py
upbankapi/const.py
upbankapi/exceptions.py
upbankapi/py.typed
upbankapi/utils.py
upbankapi/client/__init__.py
upbankapi/client/_async.py
upbankapi/client/_sync.py
upbankapi/client/base.py
upbankapi/models/__init__.py
upbankapi/models/accounts.py
upbankapi/models/categories.py
upbankapi/models/common.py
upbankapi/models/pagination.py
upbankapi/models/transactions.py
upbankapi/models/webhooks.py
up_bank_api-1.2.0.dist-info/METADATA
up_bank_api-1.2.0.dist-info/WHEEL
up_bank_api-1.2.0.dist-info/licenses/LICENSE
up_bank_api-1.2.0.dist-info/RECORD
