Metadata-Version: 2.3
Name: up-bank-api
Version: 1.2.0
Summary: 💎 Typed python client for Up's banking API
Project-URL: Homepage, https://jcwillox.github.io/up-bank-api
Project-URL: Documentation, https://jcwillox.github.io/up-bank-api
Project-URL: Repository, https://github.com/jcwillox/up-bank-api
Project-URL: Release Notes, https://github.com/jcwillox/up-bank-api/releases
Project-URL: Issues, https://github.com/jcwillox/up-bank-api/issues
Project-URL: Funding, https://ko-fi.com/jcwillox
Author-email: Josh Willox <joshwillox@gmail.com>
Classifier: Development Status :: 5 - Production/Stable
Classifier: License :: OSI Approved :: MIT License
Classifier: Operating System :: OS Independent
Classifier: Programming Language :: Python :: 3.8
Classifier: Programming Language :: Python :: 3.9
Classifier: Programming Language :: Python :: 3.10
Classifier: Programming Language :: Python :: 3.11
Classifier: Programming Language :: Python :: 3.12
Classifier: Typing :: Typed
Requires-Python: >=3.8
Requires-Dist: requests>=2.32.3
Provides-Extra: async
Requires-Dist: aiohttp>=3.10.11; extra == 'async'
